---
title: JVM-JVM字节码指令集
date: 2017-11-16 15:00:49
tags: [Java,JVM]
categories: JVM
---

下文局部变量表的索引的基本单位是Slot。例如局部变量表依序存储着long及int两个变量。则索引0及索引1处存放long，索引2处存放int。

<!-- more -->

**0x00(nop)**:什么都不做

**0x01(aconst_null)**:将null压入操作数栈

**0x02(iconst_m1)**:将int型-1压入操作数栈

**0x03(iconst_0)**:将int型0压入操作数栈

**0x04(iconst_1)**:将int型1压入操作数栈

**0x05(iconst_2)**:将int型2压入操作数栈

**0x06(iconst_3)**:将int型3压入操作数栈

**0x07(iconst_4)**:将int型4压入操作数栈

**0x08(iconst_5)**:将int型5压入操作数栈

**0x09(lconst_0)**:将long型0压入操作数栈

**0x0a(lconst_1)**:将long型1压入操作数栈

**0x0b(fconst_0)**:将float型0压入操作数栈

**0x0c(fconst_1)**:将float型1压入操作数栈

**0x0d(fconst_2)**:将float型2压入操作数栈

**0x0e(dconst_0)**:将double型0压入操作数栈

**0x0f(dconst_1)**:将double型1压入操作数栈

**0x10(bipush)**:将一个byte型的常量值(范围[-128,127])压入操作数栈，需一个操作数指明压入的值

**0x11(sipush)**:将一个short型的常量值(范围[-32768,32767])压入操作数栈，需一个操作数指明压入的值

**0x12(ldc)**:将int,float或String型常量值从常量池中推送至操作数栈栈顶。该指令的操作码之后会紧跟一个u2的操作数作为具体的值，该参数指向常量池集合中的一个对应类型的索引项

**0x13(ldc_w)**:将int,float或String型常量值从常量池中推送至操作数栈栈顶(宽索引)

**0x14(ldc2_w)**:将long或doble型常量值从常量池中推送至操作数栈栈顶(宽索引)

**0x15(iload)**:将局部变量表x号索引位置的int型数值压入操作数栈。需1个操作数指明x

**0x16(lload)**:将局部变量表x号索引位置的long型数值压入操作数栈。需1个操作数指明x

**0x17(fload)**:将局部变量表x号索引位置的float型数值压入操作数栈。需1个操作数指明x

**0x18(dload)**:将局部变量表x号索引位置的double型数值压入操作数栈。需1个操作数指明x

**0x19(aload)**:将局部变量表x号索引位置的引用类型压入操作数栈。需1个操作数指明x

**0x1a(iload_0)**:将局部变量表0号索引位置的int型数值压入操作数栈

**0x1b(iload_1)**:将局部变量表1号索引位置的int型数值压入操作数栈

**0x1c(iload_2)**:将局部变量表2号索引位置的int型数值压入操作数栈

**0x1d(iload_3)**:将局部变量表3号索引位置的int型数值压入操作数栈

**0x1e(lload_0)**:将局部变量表0号索引位置的long型数值压入操作数栈

**0x1f(lload_1)**:将局部变量表1号索引位置的long型数值压入操作数栈

**0x20(lload_2)**:将局部变量表2号索引位置的long型数值压入操作数栈

**0x21(lload_3)**:将局部变量表3号索引位置的long型数值压入操作数栈

**0x22(fload_0)**:将局部变量表0号索引位置的float型数值压入操作数栈

**0x23(fload_1)**:将局部变量表1号索引位置的float型数值压入操作数栈

**0x24(fload_2)**:将局部变量表2号索引位置的float型数值压入操作数栈

**0x25(fload_3)**:将局部变量表3号索引位置的float型数值压入操作数栈

**0x26(dload_0)**:将局部变量表0号索引位置的double型数值压入操作数栈

**0x27(dload_1)**:将局部变量表1号索引位置的double型数值压入操作数栈

**0x28(dload_2)**:将局部变量表2号索引位置的double型数值压入操作数栈

**0x29(dload_3)**:将局部变量表3号索引位置的double型数值压入操作数栈

**0x2a(aload_0)**:将局部变量表0号Slot中的引用类型压入操作数栈

**0x2b(aload_1)**:将局部变量表1号Slot中的引用类型压入操作数栈

**0x2c(aload_2)**:将局部变量表2号Slot中的引用类型压入操作数栈

**0x2d(aload_3)**:将局部变量表3号Slot中的引用类型压入操作数栈

**0x2e(iaload)**:将int型数组指定索引的值压入操作数栈

**0x2f(laload)**:将long型数组指定索引的值压入操作数栈

**0x30(faload)**:将float型数组指定索引的值压入操作数栈

**0x31(daload)**:将double型数组指定索引的值压入操作数栈

**0x32(aaload)**:将引用类型数组指定索引的值压入操作数栈

**0x33(baload)**:将byte型数组指定索引的值压入操作数栈

**0x34(caload)**:将char型数组指定索引的值压入操作数栈

**0x35(saload)**:将short型数组指定索引的值压入操作数栈

**0x36(istore)**:将栈顶int型数值弹出并存入局部变量表x号索引处。需1个操作数指明x

**0x37(lstore)**:将栈顶long型数值弹出并存入局部变量表x号索引处。需1个操作数指明x

**0x38(fstore)**:将栈顶float型数值弹出并存入局部变量表x号索引处。需1个操作数指明x

**0x39(dstore)**:将栈顶double型数值弹出并存入局部变量表x号索引处。需1个操作数指明x

**0x3a(astore)**:将栈顶引用类型弹出并存入局部变量表x号索引处。需1个操作数指明x

**0x3b(istore_0)**:将栈顶int型数值弹出并存入局部变量表0号索引处

**0x3c(istore_1)**:将栈顶int型数值弹出并存入局部变量表1号索引处

**0x3d(istore_2)**:将栈顶int型数值弹出并存入局部变量表2号索引处

**0x3e(istore_3)**:将栈顶int型数值弹出并存入局部变量表3号索引处

**0x3f(lstore_0)**:将栈顶long型数值弹出并存入局部变量表0号索引处

**0x40(lstore_1)**:将栈顶long型数值弹出并存入局部变量表1号索引处

**0x41(lstore_2)**:将栈顶long型数值弹出并存入局部变量表2号索引处

**0x42(lstore_3)**:将栈顶long型数值弹出并存入局部变量表3号索引处

**0x43(fstore_0)**:将栈顶float型数值弹出并存入局部变量表0号索引处

**0x44(fstore_1)**:将栈顶float型数值弹出并存入局部变量表1号索引处

**0x45(fstore_2)**:将栈顶float型数值弹出并存入局部变量表2号索引处

**0x46(fstore_3)**:将栈顶float型数值弹出并存入局部变量表3号索引处

**0x47(dstore_0)**:将栈顶double型数值弹出并存入局部变量表0号索引处

**0x48(dstore_1)**:将栈顶double型数值弹出并存入局部变量表1号索引处

**0x49(dstore_2)**:将栈顶double型数值弹出并存入局部变量表2号索引处

**0x4a(dstore_3)**:将栈顶double型数值弹出并存入局部变量表3号索引处

**0x4b(astore_0)**:将栈顶引用类型弹出并存入局部变量表0号索引处

**0x4c(astore_1)**:将栈顶引用类型弹出并存入局部变量表1号索引处

**0x4d(astore_2)**:将栈顶引用类型弹出并存入局部变量表2号索引处

**0x4e(astore_3)**:将栈顶引用类型弹出并存入局部变量表3号索引处

**0x4f(iastore)**:将操作数栈栈顶int型数值弹出并存入指定int型数组的指定索引位置

**0x50(lastore)**:将操作数栈栈顶long型数值弹出并存入指定long型数组的指定索引位置

**0x51(fastore)**:将操作数栈栈顶float型数值弹出并存入指定float型数组的指定索引位置

**0x52(dastore)**:将操作数栈栈顶double型数值弹出并存入指定double型数组的指定索引位置

**0x53(aastore)**:将操作数栈栈顶引用类型数值弹出并存入指定引用类型数组的指定索引位置

**0x54(bastore)**:将栈顶byte型数值存入指定数组的指定索引位置

**0x55(castore)**:将栈顶char型数值存入指定数组的指定索引位置

**0x56(sastore)**:将栈顶short型数值存入指定数组的指定索引位置

**0x57(pop)**:将操作数栈栈顶数值弹出(数值不能是long或double)

**0x58(pop2)**:将操作数栈栈顶数值弹出(long或double)或顶部两个数值弹出(非long或double)

**0x59(dup)**:弹出操作数栈栈顶数值，复制该值并将原值及复制值压入操作数栈

**0x5a(dup_x1)**:复制操作数栈栈顶数值并将两个复制值压入操作数栈

**0x5b(dup_x2)**:复制操作数栈栈顶数值并将三个(或两个)复制值压入操作数栈

**0x5c(dup2)**:复制栈顶一个(long或double)或两个(非long或double)数值并将复制值压入操作数栈

**0x5d(dup2_x1)**:dup_x1指令的双倍版本

**0x5e(dup2_x2)**:dup_x2指令的双倍版本

**0x5f(swap)**:将操作数栈最顶端的两个数值交换(不能是long或double)

**0x60(iadd)**:弹出操作数栈栈顶两int型数值相加并将结果压入操作数栈

**0x61(ladd)**:弹出操作数栈栈顶两long型数值相加并将结果压入操作数栈

**0x62(fadd)**:弹出操作数栈栈顶两float型数值相加并将结果压入操作数栈

**0x63(dadd)**:弹出操作数栈栈顶两double型数值相加并将结果压入操作数栈

**0x64(isub)**:弹出操作数栈栈顶两int型数值相减并将结果压入操作数栈

**0x65(lsub)**:弹出操作数栈栈顶两long型数值相减并将结果压入操作数栈

**0x66(fsub)**:弹出操作数栈栈顶两float型数值相减并将结果压入操作数栈

**0x67(dsub)**:弹出操作数栈栈顶两double型数值相减并将结果压入操作数栈

**0x68(imul)**:弹出操作数栈栈顶两int型数值相乘并将结果压入操作数栈

**0x69(lmul)**:弹出操作数栈栈顶两long型数值相乘并将结果压入操作数栈

**0x6a(fmul)**:弹出操作数栈栈顶两float型数值相乘并将结果压入操作数栈

**0x6b(dmul)**:弹出操作数栈栈顶两double型数值相乘并将结果压入操作数栈

**0x6c(idiv)**:弹出操作数栈栈顶两int型数值相除并将结果压入操作数栈

**0x6d(ldiv)**:弹出操作数栈栈顶两long型数值相除并将结果压入操作数栈

**0x6e(fdiv)**:弹出操作数栈栈顶两float型数值相除并将结果压入操作数栈

**0x6f(ddiv)**:弹出操作数栈栈顶两double型数值相除并将结果压入操作数栈

**0x70(irem)**:弹出操作数栈栈顶两int型数值取余并将结果压入操作数栈

**0x71(lrem)**:弹出操作数栈栈顶两long型数值取余并将结果压入操作数栈

**0x72(frem)**:弹出操作数栈栈顶两float型数值取余并将结果压入操作数栈

**0x73(drem)**:弹出操作数栈栈顶两double型数值取余并将结果压入操作数栈

**0x74(ineg)**:弹出操作数栈栈顶int型数值取反并将结果压入操作数栈

**0x75(lneg)**:弹出操作数栈栈顶long型数值取反并将结果压入操作数栈

**0x76(fneg)**:弹出操作数栈栈顶float型数值取反并将结果压入操作数栈

**0x77(dneg)**:弹出操作数栈栈顶double型数值取反并将结果压入操作数栈

**0x78(ishl)**:弹出操作数栈栈顶int型数值左移x位并将结果压入操作数栈。需1个操作数指明x

**0x79(lshl)**:弹出操作数栈栈顶long型数值左移x位并将结果压入操作数栈。需1个操作数指明x

**0x7a(ishr)**:弹出操作数栈栈顶int型数值右移x位(有符号位移，符号位不变)并将结果压入操作数栈。需1个操作数指明x

**0x7b(lshr)**:弹出操作数栈栈顶long型数值右移x位(有符号位移，符号位不变)并将结果压入操作数栈。需1个操作数指明x

**0x7c(iushr)**:弹出操作数栈栈顶int型数值右移x位(无符号位移，符号位也移动)并将结果压入操作数栈。需1个操作数指明x

**0x7d(lushr)**:弹出操作数栈栈顶long型数值右移x位(无符号位移，符号位也移动)并将结果压入操作数栈。需1个操作数指明x

**0x7e(iand)**:弹出操作数栈栈顶两int型数值按位与并将结果压入操作数栈

**0x7f(land)**:弹出操作数栈栈顶两long型数值按位与并将结果压入操作数栈

**0x80(ior)**:弹出操作数栈栈顶两int型数值按位或并将结果压入操作数栈

**0x81(lor)**:弹出操作数栈栈顶两long型数值按位或并将结果压入操作数栈

**0x82(ixor)**:弹出操作数栈栈顶两int型数值按位异或并将结果压入操作数栈

**0x83(lxor)**:弹出操作数栈栈顶两long型数值按位异或并将结果压入操作数栈

**0x84(iinc)**:将指定int型变量增加指定值(如i++,i–-,i+=2等)

**0x85(i2l)**:弹出操作数栈栈顶int型数值强制转换成long型数值并将结果压入操作数栈

**0x86(i2f)**:弹出操作数栈栈顶int型数值强制转换成float型数值并将结果压入操作数栈

**0x87(i2d)**:弹出操作数栈栈顶int型数值强制转换成double型数值并将结果压入操作数栈

**0x88(l2i)**:弹出操作数栈栈顶long型数值强制转换成int型数值并将结果压入操作数栈

**0x89(l2f)**:弹出操作数栈栈顶long型数值强制转换成float型数值并将结果压入操作数栈

**0x8a(l2d)**:弹出操作数栈栈顶long型数值强制转换成double型数值并将结果压入操作数栈

**0x8b(f2i)**:弹出操作数栈栈顶float型数值强制转换成int型数值并将结果压入操作数栈

**0x8c(f2l)**:弹出操作数栈栈顶float型数值强制转换成long型数值并将结果压入操作数栈

**0x8d(f2d)**:弹出操作数栈栈顶float型数值强制转换成double型数值并将结果压入操作数栈

**0x8e(d2i)**:弹出操作数栈栈顶double型数值强制转换成int型数值并将结果压入操作数栈

**0x8f(d2l)**:弹出操作数栈栈顶double型数值强制转换成long型数值并将结果压入操作数栈

**0x90(d2f)**:弹出操作数栈栈顶double型数值强制转换成float型数值并将结果压入操作数栈

**0x91(i2b)**:弹出操作数栈栈顶int型数值强制转换成byte型数值并将结果压入操作数栈

**0x92(i2c)**:弹出操作数栈栈顶int型数值强制转换成char型数值并将结果压入操作数栈

**0x93(i2s)**:弹出操作数栈栈顶int型数值强制转换成short型数值并将结果压入操作数栈

**0x94(lcmp)**:弹出并比较操作数栈栈顶两long型数值的大小，并将int型结果[1,0,-1]压入操作数栈

**0x95(fcmpl)**:弹出并比较操作数栈栈顶两float型数值的大小，并将int型结果[1,0,-1]压入操作数栈。当其中一个数值为NaN时，压入-1

**0x96(fcmpg)**:弹出并比较操作数栈栈顶两float型数值的大小，并将int型结果[1,0,-1]压入操作数栈。当其中一个数值为NaN时，压入1

**0x97(dcmpl)**:弹出并比较操作数栈栈顶两double型数值的大小，并将int型结果[1,0,-1]压入操作数栈。当其中一个数值为NaN时，压入-1

**0x98(dcmpg)**:弹出并比较操作数栈栈顶两double型数值的大小，并将int型结果[1,0,-1]压入操作数栈。当其中一个数值为NaN时，压入1

**0x99(ifeq)**:当操作数栈栈顶int型数值等于0时跳转

**0x9a(ifne)**:当操作数栈栈顶int型数值不等于0时跳转

**0x9b(iflt)**:当操作数栈栈顶int型数值小于0时跳转

**0x9c(ifge)**:当操作数栈栈顶int型数值大于等于0时跳转

**0x9d(ifgt)**:当操作数栈栈顶int型数值大于0时跳转

**0x9e(ifle)**:当操作数栈栈顶int型数值小于等于0时跳转

**0x9f(if_icmpeq)**:比较操作数栈栈顶两int型数值大小，当结果等于0时跳转

**0xa0(if_icmpne)**:比较操作数栈栈顶两int型数值大小，当结果不等于0时跳转

**0xa1(if_icmplt)**:比较操作数栈栈顶两int型数值大小，当结果小于0时跳转

**0xa2(if_icmpge)**:比较操作数栈栈顶两int型数值大小，当结果大于等于0时跳转

**0xa3(if_icmpgt)**:比较操作数栈栈顶两int型数值大小，当结果大于0时跳转

**0xa4(if_icmple)**:比较操作数栈栈顶两int型数值大小，当结果小于等于0时跳转

**0xa5(if_acmpeq)**:比较操作数栈栈顶两引用类型数值，当结果相等时跳转

**0xa6(if_acmpne)**:比较操作数栈栈顶两引用类型数值，当结果不相等时跳转

**0xa7(goto)**:无条件跳转，后续需跟随行号作为跳转位置

**0xa8(jsr)**:跳转至指定16位offset位置，并将jsr下一条指令地址压入操作数栈(JDK1.7已废弃该指令)

**0xa9(ret)**:返回至本地变量(JDK1.7已废弃该指令)

**0xaa(tableswitch)**:用于switch条件跳转，case值连续(可变长度指令)

**0xab(lookupswitch)**:用于switch条件跳转，case值不连续(可变长度指令)

**0xac(ireturn)**:弹出并返回操作数栈栈顶的int类型数值

**0xad(lreturn)**:弹出并返回操作数栈栈顶的long类型数值

**0xae(freturn)**:弹出并返回操作数栈栈顶的float类型数值

**0xaf(dreturn)**:弹出并返回操作数栈栈顶的double类型数值

**0xb0(areturn)**:弹出并返回操作数栈栈顶的引用类型数值

**0xb1(return)**:从当前方法返回void，本方法结束

**0xb2(getstatic)**:获取指定类的指定类变量，并将其值压入操作数栈。该指令的操作码之后会紧跟一个u2的操作数说明具体需要的是哪个类变量，该参数指向常量池集合中的一个CONSTANT_UTF8_info类型的索引项，也就是该字段的字段符号引用

**0xb3(putstatic)**:为指定类的指定类变量赋值

**0xb4(getfield)**:获取指定类的指定实例的实例变量，并将其值压入操作数栈

**0xb5(putfield)**:为指定类的指定实例变量赋值

**0xb6(invokevirtual)**:调用实例方法。会根据对象的实际类型进行动态单分派(虚方法分派)

**0xb7(invokespecial)**:以操作数栈栈顶reference类型的数据所指向的对象为方法的接收者，调用此对象的实例构造器&lt;init&gt;方法，私有方法或超类构造方法。该指令的操作码之后会紧跟一个u2的操作数说明具体调用的是哪个方法，该参数指向常量池集合中的一个CONSTANT_UTF8_info类型的索引项，也就是该方法的方法符号引用

**0xb8(invokestatic)**:调用类方法(static修饰的方法)

**0xb9(invokeinterface)**:调用接口方法。运行期解释器会搜索一个实现了该接口方法的对象，并调用对应实现的接口方法

**0xba(–)**:无此指令

**0xbb(new)**:创建一个对象，并将其引用值压入操作数栈

**0xbc(newarray)**:创建一个指定原始类型(如int,float,char等)的数组，并将其引用值压入操作数栈

**0xbd(anewarray)**:创建一个指定引用类型(如类，接口，数组)的数组，并将其引用值压入操作数栈

**0xbe(arraylength)**:获得数组的长度并压入操作数栈栈顶。后面需跟随一个数组类型的对象

**0xbf(athrow)**:弹出操作数栈栈顶的异常并将其抛出

**0xc0(checkcast)**:检验类实例的类型转换，检验未通过将抛出ClassCastException

**0xc1(instanceof)**:检验类实例是否是指定类的实例，如果是将int型1压入操作数栈，反之压入0

**0xc2(monitorenter)**:弹出并获得操作数栈栈顶对象的管程，用于被synchronized关键字修饰的同步块

**0xc3(monitorexit)**:弹出并释放操作数栈栈顶对象的管程，用于被synchronized关键字修饰的同步块

**0xc4(wide)**:扩展本地变量的宽度

**0xc5(multianewarray)**:创建指定类型和指定维度的多维数组(执行该指令时，操作栈中必须包含各维度的长度值)，并将其引用值压入操作数栈

**0xc6(ifnull)**:操作数栈栈顶为null时跳转

**0xc7(ifnonnull)**:操作数栈栈顶不为null时跳转

**0xc8(goto_w)**:无条件跳转(宽索引)

**0xc9(jsr_w)**:跳转至指定32位offset位置，并将jsr_w下一条指令地址压入操作数栈(JDK1.7已废弃该指令)